Workbook

Sheet Index
B2: Apex Solutions Inc.
B3: Financial Model — 9-Step Step-by-Step Build
B4: Prepared by: Equity Research Analyst, Capital Partners | 3-yr Historical + 5-yr Forecast ($ millions)
B6: Tab | C6: Description
B7: Assumptions | C7: Step 1 — All key drivers: growth rates, margins, SG&A %, D&A %, tax rate, working-capital days, debt terms
B8: Income Statement | C8: Steps 3-4 — Revenue by segment, COGS, gross margin, EBITDA, EBIT, EBT, tax, Net Income (3yr actual + 5yr forecast)
B9: Depreciation & Capex | C9: Step 5 — Supporting schedule: capex, beginning/ending Net PP&E, depreciation & amortization
B10: Working Capital | C10: Step 6 — Supporting schedule: DSO/DIO/DPO, Accounts Receivable, Inventory, Accounts Payable, cash conversion cycle
B11: Cash Flow Statement | C11: Step 7 — Indirect-method CFO/CFI/CFF, net change in cash, ending cash balance
B12: Debt Schedule | C12: Step 8 — Term loan roll-forward, interest expense, interest income on cash
B13: Balance Sheet | C13: Step 9 — Fully linked & balanced (Assets = Liabilities + Equity), plus key liquidity/leverage/ROE ratios
B15: Color Coding Convention
B16: Blue text | C16: Hardcoded inputs / actuals / assumptions
B17: Black text | C17: Formulas & calculations
B18: Green text | C18: Links pulled from another worksheet
B19: Yellow highlight | C19: Balance-check cell to monitor (should equal 0)

Sheet Assumptions
A1: Apex Solutions Inc. — Key Forecast Assumptions
A2: Step 1: Build structure & inputs. Per management guidance (MD&A) used to drive the 5-year forecast.
A4: Assumption | B4: Value | C4: Notes / Source
A5: Revenue growth — Software | B5: 0.2 | C5: Management guidance: Software segment to grow 20% p.a. over next 5 years
A6: Revenue growth — Hardware | B6: 0.18 | C6: Management guidance: Hardware segment to grow 18% p.a.
A7: Revenue growth — IT Services | B7: 0.16 | C7: Management guidance: IT Services segment to grow 16% p.a.
A8: COGS % of revenue — Software | B8: 0.5 | C8: Management target: maintain COGS at 50% via streamlined product dev & licensing
A9: COGS % of revenue — Hardware | B9: 0.48 | C9: Management target: maintain stable COGS at 48%
A10: COGS % of revenue — IT Services | B10: 0.5 | C10: Management target: maintain COGS at 50%
A11: SG&A % of total revenue | B11: 0.15 | C11: Management guidance: SG&A projected at 15% of total revenue annually
A12: D&A % of total revenue | B12: 0.045 | C12: Derived from 3-yr historical average (D&A / Revenue)
A13: Effective tax rate | B13: 0.234 | C13: Average of 3-yr historical effective tax rate
A14: Days Sales Outstanding (DSO) | B14: 19 | C14: Management target collection period
A15: Days Inventory Outstanding (DIO) | B15: 70 | C15: Management target inventory processing period
A16: Days Payable Outstanding (DPO) | B16: 48 | C16: Management target payment period
... A21: Dividend payout | B21: 0 | C21: Assumption: no dividends; 100% of net income retained

Sheet Income Statement
A1: Apex Solutions Inc.
A2: Income Statement ($ millions)
B5: FY21A | C5: FY22A | D5: FY23A | E5: FY24F | F5: FY25F | G5: FY26F | H5: FY27F | I5: FY28F
B6: Historical (Actual) | E6: Forecast
A7: Revenue
A8: Software | B8: 12000 | C8: 15000 | D8: 18500 | E8: =D8*(1+Assumptions!$B$5) | F8: =E8*(1+Assumptions!$B$5) | G8: =F8*(1+Assumptions!$B$5) | H8: =G8*(1+Assumptions!$B$5) | I8: =H8*(1+Assumptions!$B$5)
A9: Hardware | B9: 8500 | C9: 10200 | D9: 12500 | E9: =D9*(1+Assumptions!$B$6) | F9: =E9*(1+Assumptions!$B$6) | G9: =F9*(1+Assumptions!$B$6) | H9: =G9*(1+Assumptions!$B$6) | I9: =H9*(1+Assumptions!$B$6)
A10: IT Services | B10: 5000 | C10: 6500 | D10: 8000 | E10: =D10*(1+Assumptions!$B$7) | F10: =E10*(1+Assumptions!$B$7) | G10: =F10*(1+Assumptions!$B$7) | H10: =G10*(1+Assumptions!$B$7) | I10: =H10*(1+Assumptions!$B$7)
A11: Total Revenue | B11: =SUM(B8:B10) | C11: =SUM(C8:C10) | D11: =SUM(D8:D10) | E11: =SUM(E8:E10) | F11: =SUM(F8:F10) | G11: =SUM(G8:G10) | H11: =SUM(H8:H10) | I11: =SUM(I8:I10)
A13: Cost of Goods Sold (COGS)
A14: Software | B14: 6000 | C14: 7500 | D14: 9250 | E14: =E8*Assumptions!$B$8 | F14: =F8*Assumptions!$B$8 | G14: =G8*Assumptions!$B$8 | H14: =H8*Assumptions!$B$8 | I14: =I8*Assumptions!$B$8
A15: Hardware | B15: 4080 | C15: 4896 | D15: 6000 | E15: =E9*Assumptions!$B$9 | F15: =F9*Assumptions!$B$9 | G15: =G9*Assumptions!$B$9 | H15: =H9*Assumptions!$B$9 | I15: =I9*Assumptions!$B$9
A16: IT Services | B16: 2500 | C16: 3250 | D16: 4000 | E16: =E10*Assumptions!$B$10 | F16: =F10*Assumptions!$B$10 | G16: =G10*Assumptions!$B$10 | H16: =H10*Assumptions!$B$10 | I16: =I10*Assumptions!$B$10
A17: Total COGS | B17: =SUM(B14:B16) | C17: =SUM(C14:C16) | D17: =SUM(D14:D16) | E17: =SUM(E14:E16) | F17: =SUM(F14:F16) | G17: =SUM(G14:G16) | H17: =SUM(H14:H16) | I17: =SUM(I14:I16)
A19: Gross Profit | B19: =B11-B17 | C19: =C11-C17 | D19: =D11-D17 | E19: =E11-E17 | F19: =F11-F17 | G19: =G11-G17 | H19: =H11-H17 | I19: =I11-I17
A20: Gross Margin % | B20: =B19/B11 | C20: =C19/C11 | D20: =D19/D11 | E20: =E19/E11 | F20: =F19/F11 | G20: =G19/G11 | H20: =H19/H11 | I20: =I19/I11
A22: SG&A | B22: 3825 | C22: 4755 | D22: 5850 | E22: =E11*Assumptions!$B$11 | F22: =F11*Assumptions!$B$11 | G22: =G11*Assumptions!$B$11 | H22: =H11*Assumptions!$B$11 | I22: =I11*Assumptions!$B$11
A24: EBITDA | B24: =B19-B22 | C24: =C19-C22 | D24: =D19-D22 | E24: =E19-E22 | F24: =F19-F22 | G24: =G19-G22 | H24: =H19-H22 | I24: =I19-I22
A25: EBITDA Margin % | B25: =B24/B11 | C25: =C24/C11 | D25: =D24/D11 | E25: =E24/E11 | F25: =F24/F11 | G25: =G24/G11 | H25: =H24/H11 | I25: =I24/I11
A27: Depreciation & Amortization | B27: ='Depreciation & Capex'!B16 | C27: ='Depreciation & Capex'!C16 | D27: ='Depreciation & Capex'!D16 | E27: ='Depreciation & Capex'!E16 | F27: ='Depreciation & Capex'!F16 | G27: ='Depreciation & Capex'!G16 | H27: ='Depreciation & Capex'!H16 | I27: ='Depreciation & Capex'!I16
A29: EBIT (Operating Profit) | B29: =B24-B27 | C29: =C24-C27 | D29: =D24-D27 | E29: =E24-E27 | F29: =F24-F27 | G29: =G24-G27 | H29: =H24-H27 | I29: =I24-I27
A30: EBIT Margin % | B30: =B29/B11 | C30: =C29/C11 | D30: =D29/D11 | E30: =E29/E11 | F30: =F29/F11 | G30: =G29/G11 | H30: =H29/H11 | I30: =I29/I11
A32: Interest Expense | B32: =-'Debt Schedule'!B13 | C32: =-'Debt Schedule'!C13 | D32: =-'Debt Schedule'!D13 | E32: =-'Debt Schedule'!E13 | F32: =-'Debt Schedule'!F13 | G32: =-'Debt Schedule'!G13 | H32: =-'Debt Schedule'!H13 | I32: =-'Debt Schedule'!I13
A33: Interest Income | B33: ='Debt Schedule'!B19 | C33: ='Debt Schedule'!C19 | D33: ='Debt Schedule'!D19 | E33: ='Debt Schedule'!E19 | F33: ='Debt Schedule'!F19 | G33: ='Debt Schedule'!G19 | H33: ='Debt Schedule'!H19 | I33: ='Debt Schedule'!I19
A35: EBT (Pre-tax Profit) | B35: =B29+B32+B33 | C35: =C29+C32+C33 | D35: =D29+D32+D33 | E35: =E29+E32+E33 | F35: =F29+F32+F33 | G35: =G29+G32+G33 | H35: =H29+H32+H33 | I35: =I29+I32+I33
A36: EBT Margin % | B36: =B35/B11 | C36: =C35/C11 | D36: =D35/D11 | E36: =E35/E11 | F36: =F35/F11 | G36: =G35/G11 | H36: =H35/H11 | I36: =I35/I11
A38: Tax | B38: 1465.9 | C38: 1870.4 | D38: 2348.8 | E38: =E35*Assumptions!$B$13 | F38: =F35*Assumptions!$B$13 | G38: =G35*Assumptions!$B$13 | H38: =H35*Assumptions!$B$13 | I38: =I35*Assumptions!$B$13
A39: Effective Tax Rate % | B39: =B38/B35 | C39: =C38/C35 | D39: =D38/D35 | E39: =E38/E35 | F39: =F38/F35 | G39: =G38/G35 | H39: =H38/H35 | I39: =I38/I35
A41: Net Income | B41: =B35-B38 | C41: =C35-C38 | D41: =D35-D38 | E41: =E35-E38 | F41: =F35-F38 | G41: =G35-G38 | H41: =H35-H38 | I41: =I35-I38
A42: Net Income Margin % | B42: =B41/B11 | C42: =C41/C11 | D42: =D41/D11 | E42: =E41/E11 | F42: =F41/F11 | G42: =G41/G11 | H42: =H41/H11 | I42: =I41/I11

Sheet Depreciation & Capex
A1: Apex Solutions Inc.
A2: Depreciation & Capex Schedule (Supporting Schedule) ($ millions)
B5: FY21A | C5: FY22A | D5: FY23A | E5: FY24F | F5: FY25F | G5: FY26F | H5: FY27F | I5: FY28F
B6: Historical (Actual) | E6: Forecast
A7: Total Revenue (linked) | B7: ='Income Statement'!B11 | C7: ='Income Statement'!C11 | D7: ='Income Statement'!D11 | E7: ='Income Statement'!E11 | F7: ='Income Statement'!F11 | G7: ='Income Statement'!G11 | H7: ='Income Statement'!H11 | I7: ='Income Statement'!I11
A9: Capital Expenditure (Capex) | B9: 8000 | C9: 9000 | D9: 9800 | E9: 10000 | F9: 11500 | G9: 13000 | H9: 13500 | I9: 15000
A11: Beginning Net PP&E | B11: 15000 | C11: =B14 | D11: =C14 | E11: =D14 | F11: =E14 | G11: =F14 | H11: =G14 | I11: =H14
A12: (+) Capex | B12: =B9 | C12: =C9 | D12: =D9 | E12: =E9 | F12: =F9 | G12: =G9 | H12: =H9 | I12: =I9
A13: (-) Depreciation & Amortization | B13: =B16 | C13: =C16 | D13: =D16 | E13: =E16 | F13: =F16 | G13: =G16 | H13: =H16 | I13: =I16
A14: Ending Net PP&E | B14: =B11+B12-B13 | C14: =C11+C12-C13 | D14: =D11+D12-D13 | E14: =E11+E12-E13 | F14: =F11+F12-F13 | G14: =G11+G12-G13 | H14: =H11+H12-H13 | I14: =I11+I12-I13
A16: Depreciation & Amortization | B16: 1147.5 | C16: 1426.5 | D16: 1755 | E16: =E7*Assumptions!$B$12 | F16: =F7*Assumptions!$B$12 | G16: =G7*Assumptions!$B$12 | H16: =H7*Assumptions!$B$12 | I16: =I7*Assumptions!$B$12
A17: D&A % of Revenue | B17: =B16/B7 | C17: =C16/C7 | D17: =D16/D7 | E17: =E16/E7 | F17: =F16/F7 | G17: =G16/G7 | H17: =H16/H7 | I17: =I16/I7
A19: Note: Amortization of intangibles assumed $0 (no intangible assets / acquisitions on balance sheet).

Sheet Working Capital
A1: Apex Solutions Inc.
A2: Working Capital Schedule (Supporting Schedule) ($ millions)
B5: FY21A | C5: FY22A | D5: FY23A | E5: FY24F | F5: FY25F | G5: FY26F | H5: FY27F | I5: FY28F
B6: Historical (Actual) | E6: Forecast
A7: Total Revenue (linked) | B7: ='Income Statement'!B11 | C7: ='Income Statement'!C11 | D7: ='Income Statement'!D11 | E7: ='Income Statement'!E11 | F7: ='Income Statement'!F11 | G7: ='Income Statement'!G11 | H7: ='Income Statement'!H11 | I7: ='Income Statement'!I11
A8: Total COGS (linked) | B8: ='Income Statement'!B17 | C8: ='Income Statement'!C17 | D8: ='Income Statement'!D17 | E8: ='Income Statement'!E17 | F8: ='Income Statement'!F17 | G8: ='Income Statement'!G17 | H8: ='Income Statement'!H17 | I8: ='Income Statement'!I17
A10: Accounts Receivable | B10: 1467 | C10: 1737 | D10: 2030 | E10: =E7*E15/365 | F10: =F7*F15/365 | G10: =G7*G15/365 | H10: =H7*H15/365 | I10: =I7*I15/365
A11: Inventory | B11: 2757 | C11: 3214 | D11: 3692 | E11: =E8*E16/365 | F11: =F8*F16/365 | G11: =G8*G16/365 | H11: =H8*H16/365 | I11: =I8*I16/365
A12: Accounts Payable | B12: 1896 | C12: 2144 | D12: 2532 | E12: =E8*E17/365 | F12: =F8*F17/365 | G12: =G8*G17/365 | H12: =H8*H17/365 | I12: =I8*I17/365
A14: Net Working Capital (AR + Inv - AP) | B14: =B10+B11-B12 | C14: =C10+C11-C12 | D14: =D10+D11-D12 | E14: =E10+E11-E12 | F14: =F10+F11-F12 | G14: =G10+G11-G12 | H14: =H10+H11-H12 | I14: =I10+I11-I12
A15: Days Sales Outstanding (DSO) | B15: =B10/B7*365 | C15: =C10/C7*365 | D15: =D10/D7*365 | E15: =Assumptions!$B$14 | F15: =Assumptions!$B$14 | G15: =Assumptions!$B$14 | H15: =Assumptions!$B$14 | I15: =Assumptions!$B$14
A16: Days Inventory Outstanding (DIO) | B16: =B11/B8*365 | C16: =C11/C8*365 | D16: =D11/D8*365 | E16: =Assumptions!$B$15 | F16: =Assumptions!$B$15 | G16: =Assumptions!$B$15 | H16: =Assumptions!$B$15 | I16: =Assumptions!$B$15
A17: Days Payable Outstanding (DPO) | B17: =B12/B8*365 | C17: =C12/C8*365 | D17: =D12/D8*365 | E17: =Assumptions!$B$16 | F17: =Assumptions!$B$16 | G17: =Assumptions!$B$16 | H17: =Assumptions!$B$16 | I17: =Assumptions!$B$16
A19: Cash Conversion Cycle (days) | B19: =B15+B16-B17 | C19: =C15+C16-C17 | D19: =D15+D16-D17 | E19: =E15+E16-E17 | F19: =F15+F16-F17 | G19: =G15+G16-G17 | H19: =H15+H16-H17 | I19: =I15+I16-I17
A21: Receivables Turnover (x) | B21: =365/B15 | C21: =365/C15 | D21: =365/D15 | E21: =365/E15 | F21: =365/F15 | G21: =365/G15 | H21: =365/H15 | I21: =365/I15
A22: Inventory Turnover (x) | B22: =365/B16 | C22: =365/C16 | D22: =365/D16 | E22: =365/E16 | F22: =365/F16 | G22: =365/G16 | H22: =365/H16 | I22: =365/I16
A23: Payables Turnover (x) | B23: =365/B17 | C23: =365/C17 | D23: =365/D17 | E23: =365/E17 | F23: =365/F17 | G23: =365/G17 | H23: =365/H17 | I23: =365/I17

Sheet Cash Flow Statement
A1: Apex Solutions Inc.
A2: Cash Flow Statement (Indirect Method) ($ millions)
B5: FY21A | C5: FY22A | D5: FY23A | E5: FY24F | F5: FY25F | G5: FY26F | H5: FY27F | I5: FY28F
B6: Historical (Actual) | E6: Forecast
A7: Cash Flow from Operating Activities
A8: Net Income | B8: ='Income Statement'!B41 | C8: ='Income Statement'!C41 | D8: ='Income Statement'!D41 | E8: ='Income Statement'!E41 | F8: ='Income Statement'!F41 | G8: ='Income Statement'!G41 | H8: ='Income Statement'!H41 | I8: ='Income Statement'!I41
A9: (+) Depreciation & Amortization | B9: ='Depreciation & Capex'!B16 | C9: ='Depreciation & Capex'!C16 | D9: ='Depreciation & Capex'!D16 | E9: ='Depreciation & Capex'!E16 | F9: ='Depreciation & Capex'!F16 | G9: ='Depreciation & Capex'!G16 | H9: ='Depreciation & Capex'!H16 | I9: ='Depreciation & Capex'!I16
A10: (-) Increase in Accounts Receivable | B10: -200 | C10: -270 | D10: -293 | E10: =-('Working Capital'!E10-'Working Capital'!D10) | F10: =-('Working Capital'!F10-'Working Capital'!E10) | G10: =-('Working Capital'!G10-'Working Capital'!F10) | H10: =-('Working Capital'!H10-'Working Capital'!G10) | I10: =-('Working Capital'!I10-'Working Capital'!H10)
A11: (-) Increase in Inventory | B11: -300 | C11: -457 | D11: -478 | E11: =-('Working Capital'!E11-'Working Capital'!D11) | F11: =-('Working Capital'!F11-'Working Capital'!E11) | G11: =-('Working Capital'!G11-'Working Capital'!F11) | H11: =-('Working Capital'!H11-'Working Capital'!G11) | I11: =-('Working Capital'!I11-'Working Capital'!H11)
A12: (+) Increase in Accounts Payable | B12: 150 | C12: 248 | D12: 388 | E12: ='Working Capital'!E12-'Working Capital'!D12 | F12: ='Working Capital'!F12-'Working Capital'!E12 | G12: ='Working Capital'!G12-'Working Capital'!F12 | H12: ='Working Capital'!H12-'Working Capital'!G12 | I12: ='Working Capital'!I12-'Working Capital'!H12
A13: Cash Flow from Operations | B13: =SUM(B8:B12) | C13: =SUM(C8:C12) | D13: =SUM(D8:D12) | E13: =SUM(E8:E12) | F13: =SUM(F8:F12) | G13: =SUM(G8:G12) | H13: =SUM(H8:H12) | I13: =SUM(I8:I12)
A15: Cash Flow from Investing Activities
A16: (-) Capital Expenditure | B16: =-'Depreciation & Capex'!B9 | C16: =-'Depreciation & Capex'!C9 | D16: =-'Depreciation & Capex'!D9 | E16: =-'Depreciation & Capex'!E9 | F16: =-'Depreciation & Capex'!F9 | G16: =-'Depreciation & Capex'!G9 | H16: =-'Depreciation & Capex'!H9 | I16: =-'Depreciation & Capex'!I9
A17: Cash Flow from Investing | B17: =B16 | C17: =C16 | D17: =D16 | E17: =E16 | F17: =F16 | G17: =G16 | H17: =H16 | I17: =I16
A19: Cash Flow from Financing Activities
A20: (+) Proceeds from New Term Loan | B20: ='Debt Schedule'!B8 | C20: ='Debt Schedule'!C8 | D20: ='Debt Schedule'!D8 | E20: ='Debt Schedule'!E8 | F20: ='Debt Schedule'!F8 | G20: ='Debt Schedule'!G8 | H20: ='Debt Schedule'!H8 | I20: ='Debt Schedule'!I8
A21: (-) Repayment of Term Loan | B21: =-'Debt Schedule'!B9 | C21: =-'Debt Schedule'!C9 | D21: =-'Debt Schedule'!D9 | E21: =-'Debt Schedule'!E9 | F21: =-'Debt Schedule'!F9 | G21: =-'Debt Schedule'!G9 | H21: =-'Debt Schedule'!H9 | I21: =-'Debt Schedule'!I9
A22: Cash Flow from Financing | B22: =B20+B21 | C22: =C20+C21 | D22: =D20+D21 | E22: =E20+E21 | F22: =F20+F21 | G22: =G20+G21 | H22: =H20+H21 | I22: =I20+I21
A24: Net Change in Cash | B24: =B13+B17+B22 | C24: =C13+C17+C22 | D24: =D13+D17+D22 | E24: =E13+E17+E22 | F24: =F13+F17+F22 | G24: =G13+G17+G22 | H24: =H13+H17+H22 | I24: =I13+I17+I22
A26: Beginning Cash & Cash Equivalents | B26: 800 | C26: =B27 | D26: =C27 | E26: =D27 | F26: =E27 | G26: =F27 | H26: =G27 | I26: =H27
A27: Ending Cash & Cash Equivalents | B27: =B26+B24 | C27: =C26+C24 | D27: =D26+D24 | E27: =E26+E24 | F27: =F26+F24 | G27: =G26+G24 | H27: =H26+H24 | I27: =I26+I24

Sheet Debt Schedule
A1: Apex Solutions Inc.
A2: Debt & Interest Schedule (Supporting Schedule) ($ millions)
B5: FY21A | C5: FY22A | D5: FY23A | E5: FY24F | F5: FY25F | G5: FY26F | H5: FY27F | I5: FY28F
B6: Historical (Actual) | E6: Forecast
A7: Beginning Term Loan Balance | B7: 18000 | C7: =B10 | D7: =C10 | E7: =D10 | F7: =E10 | G7: =F10 | H7: =G10 | I7: =H10
A8: (+) New Issuance | B8: 2200 | C8: 2700 | D8: 3000 | E8: =Assumptions!$B$20 | F8: =Assumptions!$B$20 | G8: =Assumptions!$B$20 | H8: =Assumptions!$B$20 | I8: =Assumptions!$B$20
A9: (-) Repayment | B9: 200 | C9: 200 | D9: 300 | E9: =Assumptions!$B$19 | F9: =Assumptions!$B$19 | G9: =Assumptions!$B$19 | H9: =Assumptions!$B$19 | I9: =Assumptions!$B$19
A10: Ending Term Loan Balance | B10: =B7+B8-B9 | C10: =C7+C8-C9 | D10: =D7+D8-D9 | E10: =E7+E8-E9 | F10: =F7+F8-F9 | G10: =G7+G8-G9 | H10: =H7+H8-H9 | I10: =I7+I8-I9
A12: Average Term Loan Balance | B12: =AVERAGE(B7,B10) | C12: =AVERAGE(C7,C10) | D12: =AVERAGE(D7,D10) | E12: =AVERAGE(E7,E10) | F12: =AVERAGE(F7,F10) | G12: =AVERAGE(G7,G10) | H12: =AVERAGE(H7,H10) | I12: =AVERAGE(I7,I10)
A13: Interest Expense | B13: =B12*Assumptions!$B$17 | C13: =C12*Assumptions!$B$17 | D13: =D12*Assumptions!$B$17 | E13: =E12*Assumptions!$B$17 | F13: =F12*Assumptions!$B$17 | G13: =G12*Assumptions!$B$17 | H13: =H12*Assumptions!$B$17 | I13: =I12*Assumptions!$B$17
A15: Beginning Cash & Cash Equivalents | B15: ='Cash Flow Statement'!B26 | C15: ='Cash Flow Statement'!C26 | D15: ='Cash Flow Statement'!D26 | E15: ='Cash Flow Statement'!E26 | F15: ='Cash Flow Statement'!F26 | G15: ='Cash Flow Statement'!G26 | H15: ='Cash Flow Statement'!H26 | I15: ='Cash Flow Statement'!I26
A16: Ending Cash & Cash Equivalents | B16: ='Cash Flow Statement'!B27 | C16: ='Cash Flow Statement'!C27 | D16: ='Cash Flow Statement'!D27 | E16: ='Cash Flow Statement'!E27 | F16: ='Cash Flow Statement'!F27 | G16: ='Cash Flow Statement'!G27 | H16: ='Cash Flow Statement'!H27 | I16: ='Cash Flow Statement'!I27
A17: Average Cash Balance (memo only) | B17: =AVERAGE(B15,B16) | C17: =AVERAGE(C15,C16) | D17: =AVERAGE(D15,D16) | E17: =AVERAGE(E15,E16) | F17: =AVERAGE(F15,F16) | G17: =AVERAGE(G15,G16) | H17: =AVERAGE(H15,H16) | I17: =AVERAGE(I15,I16)
A19: Interest Income | B19: =B15*Assumptions!$B$18 | C19: =C15*Assumptions!$B$18 | D19: =D15*Assumptions!$B$18 | E19: =E15*Assumptions!$B$18 | F19: =F15*Assumptions!$B$18 | G19: =G15*Assumptions!$B$18 | H19: =H15*Assumptions!$B$18 | I19: =I15*Assumptions!$B$18

Sheet Balance Sheet
A1: Apex Solutions Inc.
A2: Balance Sheet ($ millions)
B5: FY21A | C5: FY22A | D5: FY23A | E5: FY24F | F5: FY25F | G5: FY26F | H5: FY27F | I5: FY28F
B6: Historical (Actual) | E6: Forecast
A7: ASSETS
A8: Cash & Cash Equivalents | B8: ='Cash Flow Statement'!B27 | C8: ='Cash Flow Statement'!C27 | D8: ='Cash Flow Statement'!D27 | E8: ='Cash Flow Statement'!E27 | F8: ='Cash Flow Statement'!F27 | G8: ='Cash Flow Statement'!G27 | H8: ='Cash Flow Statement'!H27 | I8: ='Cash Flow Statement'!I27
A9: Accounts Receivable | B9: ='Working Capital'!B10 | C9: ='Working Capital'!C10 | D9: ='Working Capital'!D10 | E9: ='Working Capital'!E10 | F9: ='Working Capital'!F10 | G9: ='Working Capital'!G10 | H9: ='Working Capital'!H10 | I9: ='Working Capital'!I10
A10: Inventory | B10: ='Working Capital'!B11 | C10: ='Working Capital'!C11 | D10: ='Working Capital'!D11 | E10: ='Working Capital'!E11 | F10: ='Working Capital'!F11 | G10: ='Working Capital'!G11 | H10: ='Working Capital'!H11 | I10: ='Working Capital'!I11
A11: Total Current Assets | B11: =SUM(B8:B10) | C11: =SUM(C8:C10) | D11: =SUM(D8:D10) | E11: =SUM(E8:E10) | F11: =SUM(F8:F10) | G11: =SUM(G8:G10) | H11: =SUM(H8:H10) | I11: =SUM(I8:I10)
A13: Net Property, Plant & Equipment | B13: ='Depreciation & Capex'!B14 | C13: ='Depreciation & Capex'!C14 | D13: ='Depreciation & Capex'!D14 | E13: ='Depreciation & Capex'!E14 | F13: ='Depreciation & Capex'!F14 | G13: ='Depreciation & Capex'!G14 | H13: ='Depreciation & Capex'!H14 | I13: ='Depreciation & Capex'!I14
A14: Goodwill | B14: 2400 | C14: 2400 | D14: 2400 | E14: 2400 | F14: 2400 | G14: 2400 | H14: 2400 | I14: 2400
A16: TOTAL ASSETS | B16: =B11+B13+B14 | C16: =C11+C13+C14 | D16: =D11+D13+D14 | E16: =E11+E13+E14 | F16: =F11+F13+F14 | G16: =G11+G13+G14 | H16: =H11+H13+H14 | I16: =I11+I13+I14
A18: LIABILITIES
A19: Accounts Payable | B19: ='Working Capital'!B12 | C19: ='Working Capital'!C12 | D19: ='Working Capital'!D12 | E19: ='Working Capital'!E12 | F19: ='Working Capital'!F12 | G19: ='Working Capital'!G12 | H19: ='Working Capital'!H12 | I19: ='Working Capital'!I12
A20: Total Current Liabilities | B20: =B19 | C20: =C19 | D20: =D19 | E20: =E19 | F20: =F19 | G20: =G19 | H20: =H19 | I20: =I19
A22: Term Loan (Long-term Debt) | B22: ='Debt Schedule'!B10 | C22: ='Debt Schedule'!C10 | D22: ='Debt Schedule'!D10 | E22: ='Debt Schedule'!E10 | F22: ='Debt Schedule'!F10 | G22: ='Debt Schedule'!G10 | H22: ='Debt Schedule'!H10 | I22: ='Debt Schedule'!I10
A24: TOTAL LIABILITIES | B24: =B20+B22 | C24: =C20+C22 | D24: =D20+D22 | E24: =E20+E22 | F24: =F20+F22 | G24: =G20+G22 | H24: =H20+H22 | I24: =I20+I22
A26: SHAREHOLDERS' EQUITY
A27: Common Stock | B27: 2000 | C27: 2000 | D27: 2000 | E27: 2000 | F27: 2000 | G27: 2000 | H27: 2000 | I27: 2000
A28: Treasury Stock | B28: -500 | C28: -500 | D28: -500 | E28: -500 | F28: -500 | G28: -500 | H28: -500 | I28: -500
A29: Retained Earnings | B29: 5473.6 | C29: 11575 | D29: 19253 | E29: =D29+'Income Statement'!E41*(1-Assumptions!$B$21) | F29: =E29+'Income Statement'!F41*(1-Assumptions!$B$21) | G29: =F29+'Income Statement'!G41*(1-Assumptions!$B$21) | H29: =G29+'Income Statement'!H41*(1-Assumptions!$B$21) | I29: =H29+'Income Statement'!I41*(1-Assumptions!$B$21)
A31: TOTAL SHAREHOLDERS' EQUITY | B31: =SUM(B27:B29) | C31: =SUM(C27:C29) | D31: =SUM(D27:D29) | E31: =SUM(E27:E29) | F31: =SUM(F27:F29) | G31: =SUM(G27:G29) | H31: =SUM(H27:H29) | I31: =SUM(I27:I29)
A33: TOTAL LIABILITIES & EQUITY | B33: =B24+B31 | C33: =C24+C31 | D33: =D24+D31 | E33: =E24+E31 | F33: =F24+F31 | G33: =G24+G31 | H33: =H24+H31 | I33: =I24+I31
A35: Balance Check (Assets - Liab. & Equity) | B35: =B16-B33 | C35: =C16-C33 | D35: =D16-D33 | E35: =E16-E33 | F35: =F16-F33 | G35: =G16-G33 | H35: =H16-H33 | I35: =I16-I33
A37: Key Ratios
A38: Current Ratio (x) | B38: =B11/B20 | C38: =C11/C20 | D38: =D11/D20 | E38: =E11/E20 | F38: =F11/F20 | G38: =G11/G20 | H38: =H11/H20 | I38: =I11/I20
A39: Quick Ratio (x) | B39: =(B8+B9)/B20 | C39: =(C8+C9)/C20 | D39: =(D8+D9)/D20 | E39: =(E8+E9)/E20 | F39: =(F8+F9)/F20 | G39: =(G8+G9)/G20 | H39: =(H8+H9)/H20 | I39: =(I8+I9)/I20
A40: Cash Ratio (x) | B40: =B8/B20 | C40: =C8/C20 | D40: =D8/D20 | E40: =E8/E20 | F40: =F8/F20 | G40: =G8/G20 | H40: =H8/H20 | I40: =I8/I20
A41: Debt / Equity (x) | B41: =B22/B31 | C41: =C22/C31 | D41: =D22/D31 | E41: =E22/E31 | F41: =F22/F31 | G41: =G22/G31 | H41: =H22/H31 | I41: =I22/I31
A42: Return on Equity (%) | B42: ='Income Statement'!B41/B31 | C42: ='Income Statement'!C41/C31 | D42: ='Income Statement'!D41/D31 | E42: ='Income Statement'!E41/E31 | F42: ='Income Statement'!F41/F31 | G42: ='Income Statement'!G41/G31 | H42: ='Income Statement'!H41/H31 | I42: ='Income Statement'!I41/I31
